configio/__init__.py
configio/jsonio.py
configio/logger.py
configio/py.typed
configio/schemas.py
configio/utils.py
configio/yamlio.py
cfgio-1.0.2.dist-info/METADATA
cfgio-1.0.2.dist-info/WHEEL
cfgio-1.0.2.dist-info/licenses/LICENSE
cfgio-1.0.2.dist-info/RECORD
