Metadata-Version: 2.4
Name: cfgio
Version: 1.0.2
Summary: Unified async JSON/YAML config I/O with routed access for files and in-memory data, featuring atomic saves and thread-offloaded parsing.
Project-URL: Homepage, https://github.com/moh-dehghan/configio
Project-URL: Repository, https://github.com/moh-dehghan/configio
Project-URL: Issues, https://github.com/moh-dehghan/configio/issues
Author-email: Moh-Dehghan <m.dehghan.2003@outlook.com>
License: MIT License
License-File: LICENSE
Keywords: async,asyncio,atomic-write,config,file-io,in-memory,json,loader,mapping,nested,path-routing,persistence,pyroute,routing,settings,yaml
Classifier: Development Status :: 4 - Beta
Classifier: Framework :: AsyncIO
Classifier: Intended Audience :: Developers
Classifier: License :: OSI Approved :: MIT License
Classifier: Operating System :: OS Independent
Classifier: Programming Language :: Python
Classifier: Programming Language :: Python :: 3
Classifier: Programming Language :: Python :: 3.10
Classifier: Programming Language :: Python :: 3.11
Classifier: Programming Language :: Python :: 3.12
Classifier: Programming Language :: Python :: 3.13
Classifier: Topic :: Internet
Classifier: Topic :: Software Development :: Libraries
Requires-Python: >=3.10
Requires-Dist: aiofiles>=23.0.0
Requires-Dist: pyroute>=1.0.0
Requires-Dist: pyyaml>=6.0.0
